{
	"users":
	[
		{
			"id": "u0001",
			"login": "Hanna",
			"email":"prostor@voz.com",
			"password": "123qwE!",
			"created_at": "2024-07-05",
			"updated_at": "2024-07-07"
		},
		{
			"id": "u0002",
			"login": "Дария",
			"email":"dary@voz.com",
			"password": "456qwE!",
			"created_at": "2024-08-05",
			"updated_at": "2024-08-05"
		}

	],
	"accounts":[
		{
			"id": "a0001",
			"user_id": "u0001",
			"name": "Наличные",
			"type": "Дебетовый",
			"icon": "far fa-money-bill-alt",
			"balans": 50485.00,
			"creates_at": "2024-07-05",
			"updated_at": ""
		},
		{
			"id": "a0002",
			"user_id": "u0001",
			"name": "карта4574",
			"type": "Накопительный",
			"icon": "fas fa-money-check",
			"balans": 1596135.26,
			"creates_at": "2024-07-05",
			"updated_at": ""
		},
		{
			"id": "a0003",
			"user_id": "u0002",
			"name": "Сбер",
			"type": "Дебетовый",
			"icon": "fas fa-money-check",
			"balans": 90258.06,
			"creates_at": "2024-08-05",
			"updated_at": ""
		}
	],
	"categories": [
		{
			"id": "C0001",
			"user_id": "u0001",
			"name": "Питание",
			"type": "Расходы",
			"icon": "fas fa-utensils",
			"created_at":"2024-07-05",
			"updated_at":""

		},
			{
			"id": "C0002",
			"user_id": "u0001",
			"name": "Заработная плата",
			"type": "Доход",
			"icon": "fas fa-hand-holding-usd",
			"created_at":"2024-30-05",
			"updated_at":""

		}
	],
	"transactions": [
		{
			"id": "t0001",
			"user_id": "u0001",
			"account_id": "a0001",
			"category_id": "C0001",
			"amount": -1200.00,
			"comment": "Теремок",
			"date": "2024-08-05",
			"created_at": "2024-07-05-20-01-52",
			"updated_at": "2024-07-05-20-01-52"

		}
	]
}
